README.rst
setup.cfg
setup.py
slack2csv/__init__.py
slack2csv/slack2csv.py
slack2csv.egg-info/PKG-INFO
slack2csv.egg-info/SOURCES.txt
slack2csv.egg-info/dependency_links.txt
slack2csv.egg-info/entry_points.txt
slack2csv.egg-info/requires.txt
slack2csv.egg-info/top_level.txt
slack2csv/tests/__init__.py
slack2csv/tests/test_slack2csv.py