Metadata-Version: 1.1
Name: slack2csv
Version: 1.0.0
Summary: A Python script to export Slack channel history to csv for reporting
Home-page: https://github.com/drazisil/slack2csv
Author: Joseph W Becher
Author-email: jwbecher@drazisil.com
License: UNKNOWN
Keywords: slack csv history export
Platform: UNKNOWN
Classifier: Development Status :: 5 - Production/Stable
Classifier: Intended Audience :: Developers
Classifier: License :: OSI Approved :: Apache Software License
Classifier: Programming Language :: Python :: 2
Classifier: Programming Language :: Python :: 2.7
Classifier: Programming Language :: Python :: 3
Classifier: Programming Language :: Python :: 3.5
Classifier: Programming Language :: Python :: 3.6
